LICENSE
README.md
notion_etl/__init__.py
notion_etl/database.py
notion_etl/loader.py
notion_etl/page.py
notion_etl/py.typed
notion_etl-0.1.3.dist-info/METADATA
notion_etl-0.1.3.dist-info/WHEEL
notion_etl-0.1.3.dist-info/licenses/LICENSE
notion_etl-0.1.3.dist-info/RECORD
