Metadata-Version: 2.4
Name: notion-etl
Version: 0.1.3
Summary: A Python package for extracting data from Notion using Polars dataframes.
Project-URL: Homepage, https://github.com/Josersanvil/notion-etl/
Project-URL: Repository, https://github.com/Josersanvil/notion-etl/
Project-URL: Issues, https://github.com/Josersanvil/notion-etl/issues
Author: Jose Sanchez
License:                     GNU GENERAL PUBLIC LICENSE
License-File: LICENSE
Requires-Python: >=3.11
Requires-Dist: notion-client==2.2.1
Requires-Dist: polars==1.29.0
